{"res/atlas/bg.atlas":["bg/",["501.png","501_1.png","502.png","503.png","andanlandian.png","btn_zhanting.png","chibang.png","clip_dianjushu.png","clip_huoxing.png","dianju.png","dianjujia.png","dianjujia2.png","dongjin.png","door.png","door0.png","door1.png","douying.png","gui.png","guichibang.png","heroBlood.png","hongtiao.png","huijia.png","huzi.png","jingyantiaodi.png","jingyantiaoguang.png","jingyantiaoshang.png","lanying.png","lvkuang.png","qianshu.png","qipaowen.png","renlankuang.png","renyan.png","rockerBall.png","rockerBg.png","rollDir.png","sanjiao.png","tantan.jpg","tianshi.png","tianshiying.png","xianglian.png","xingyunda.png","xuetiaodi.png","xuetiaogang.png","xuetiaoshang.png","xuetiaoshanghong.png","yingzi.png","zhanting.png","zhen.png","zhuan_baoji.png","zhuan_jiaxue.png","zhuan_qianer.png","zhuan_qiansan.png","zhuan_qianyi.png","zhuan_xixue.png","zhuanpan.png","zhuanpan2.png"]],"res/atlas/icons/skill.atlas":["icons/skill/",["1001.jpg","1002.jpg","1003.jpg","1004.jpg","1005.jpg","1006.jpg","1007.jpg","1008.jpg","1009.jpg","2001.jpg","2002.jpg","2003.jpg","2004.jpg","2005.jpg","2006.jpg","2007.jpg","2008.jpg","3001.jpg","3002.jpg","3003.jpg","3004.jpg","3005.jpg","3006.jpg","3007.jpg","3008.jpg","4001.jpg","4002.jpg","4003.jpg","4004.jpg","4005.jpg","5001.jpg","5002.jpg","5003.jpg","5004.jpg","5005.jpg","5006.jpg","5007.jpg","5008.jpg","5009.jpg"]],"res/atlas/jiesuan.atlas":["jiesuan/",["baifen.png","heipai.png","lanbu.png","shanglian.png","xianglian.png","youtiao.png","zhanlipin.png","zuotiao.png"]],"res/atlas/main.atlas":["main/",["JYtian.png","PTtian.png","SStian.png","action.png","anniudian.png","biaoti.png","biaotifuhuo.png","biaotihong.png","biaotihuang.png","biaotilan.png","biaotitishi.png","btn_0.png","btn_1.png","btn_2.png","btn_3.png","btn_4.png","btn_fuhuo.png","btn_guanbi.png","btn_hong.png","btn_huang.png","btn_lan.png","btn_lv.png","changhong.png","clipshuzi.png","dabiao.png","dazhao.png","dengji.png","diandian.png","diban.png","dongjin.png","erdao.png","fuhuodi2.jpg","greenFont.png","guangdian.png","haibo.png","jianhei.png","jindutiao.png","jindutiaolan.png","jingyantiaodi.png","jingyantiaoshang.png","jujue.png","kapai.png","kawen.png","maohao.png","qing.png","queding.png","quxiao.png","redFont.png","shamolvzhou.png","shandianjia.png","shengji.png","shuaxin.png","shukuang.png","suo.png","suo2.png","tili.png","tishilan.png","toujian.png","touxiangdi.png","touxiangkuang.png","wenhao.png","xiaobiao.png","xiegang.png","xuxian.png","zhudi.jpg","zuanshijia.png"]],"res/atlas/map_1.atlas":["map_1/",["100.png","201.png","202.png","203.png","204.png","205.png","206.png","207.png","208.png","209.png","301.png","302.png","303.png","401.png","402.png","403.png","404.png","500.png","804.png","901.png","902.png","903.png","904.png","906.png","907.png","908.png","909.png","shitouying.png","tongying.png"]],"res/atlas/map_2.atlas":["map_2/",["10.png","100.png","11.png","201.png","202.png","203.png","204.png","205.png","206.png","207.png","208.png","209.png","301.png","302.png","303.png","401.png","402.png","403.png","404.png","500.png","804.png","901.png","902.png","903.png","904.png","906.png","907.png","908.png","909.png","border.png","bosstou.png","bottom.png","shitouying.png","top.png"]],"res/atlas/map_3.atlas":["map_3/",["10.png","100.png","11.png","201.png","202.png","203.png","204.png","205.png","206.png","207.png","208.png","209.png","301.png","302.png","303.png","401.png","402.png","403.png","404.png","500.png","804.png","border.png","bosstou.png","bottom.png","shitouying.png","top.png"]],"res/atlas/shengli.atlas":["shengli/",["chengli.png","dunpai.png","guangzhuan1.png","haojiao.png","qi.png"]],"res/atlas/zhaohuan.atlas":["zhaohuan/",["guangzhu.png","yuandi.png","yun.png"]]}